truenas_unlock.py
truenas_unlock-1.7.0.dist-info/METADATA
truenas_unlock-1.7.0.dist-info/WHEEL
truenas_unlock-1.7.0.dist-info/entry_points.txt
truenas_unlock-1.7.0.dist-info/licenses/LICENSE
truenas_unlock-1.7.0.dist-info/RECORD
