Metadata-Version: 2.4
Name: truenas-unlock
Version: 1.7.0
Summary: Unlock encrypted ZFS datasets on TrueNAS via the API
Project-URL: Homepage, https://github.com/basnijholt/truenas-unlock
Project-URL: Repository, https://github.com/basnijholt/truenas-unlock
Project-URL: Issues, https://github.com/basnijholt/truenas-unlock/issues
Author-email: Bas Nijholt <bas@nijho.lt>
License: MIT
License-File: LICENSE
Keywords: encryption,nas,truenas,unlock,zfs
Classifier: Development Status :: 4 - Beta
Classifier: Environment :: Console
Classifier: Intended Audience :: System Administrators
Classifier: License :: OSI Approved :: MIT License
Classifier: Operating System :: OS Independent
Classifier: Programming Language :: Python :: 3
Classifier: Programming Language :: Python :: 3.11
Classifier: Programming Language :: Python :: 3.12
Classifier: Programming Language :: Python :: 3.13
Classifier: Programming Language :: Python :: 3.14
Classifier: Topic :: System :: Systems Administration
Classifier: Typing :: Typed
Requires-Python: >=3.11
Requires-Dist: httpx>=0.25
Requires-Dist: pydantic>=2.0
Requires-Dist: pyyaml>=6.0
Requires-Dist: rich>=13.0
Requires-Dist: typer>=0.9
